naivedatetimefield/__init__.py
tests/__init__.py
tests/models.py
tests/settings.py
tests/tests.py
django_naivedatetimefield-2.0.1.dist-info/LICENSE
django_naivedatetimefield-2.0.1.dist-info/METADATA
django_naivedatetimefield-2.0.1.dist-info/WHEEL
django_naivedatetimefield-2.0.1.dist-info/top_level.txt
django_naivedatetimefield-2.0.1.dist-info/RECORD
